Metadata-Version: 1.1
Name: buffered-smtp-handler
Version: 0.1.0
Summary: A buffered logging handlers that mimics SMTPHandler
Home-page: https://github.com/pierky/bufferedsmtphandler
Author: Pier Carlo Chiodi
Author-email: pierky@pierky.com
License: GPLv3
Download-URL: https://github.com/pierky/bufferedsmtphandler
Keywords: logging,python
Platform: UNKNOWN
Classifier: Development Status :: 4 - Beta
Classifier: Environment :: Console
Classifier: Intended Audience :: Information Technology
Classifier: Intended Audience :: System Administrators
Classifier: Intended Audience :: Telecommunications Industry
Classifier: Intended Audience :: Developers
Classifier: License :: OSI Approved :: GNU General Public License v3 (GPLv3)
Classifier: Operating System :: POSIX
Classifier: Operating System :: Unix
Classifier: Programming Language :: Python
Classifier: Programming Language :: Python :: 2.7
Classifier: Programming Language :: Python :: 3.4
Classifier: Topic :: Internet :: WWW/HTTP
Classifier: Topic :: System :: Networking
Classifier: Topic :: Software Development :: Libraries
Classifier: Topic :: Software Development :: Libraries :: Python Modules
Classifier: Topic :: System :: Logging
